todo_cli/__init__.py
todo_cli/calendar_interactive.py
todo_cli/calendar_view.py
todo_cli/config.py
todo_cli/cycles.py
todo_cli/database.py
todo_cli/display.py
todo_cli/export.py
todo_cli/interactive.py
todo_cli/kanban.py
todo_cli/kanban_tui.py
todo_cli/main.py
todo_cli/migrations.py
todo_cli/models.py
todo_cli/projects.py
todo_cli/recurrence.py
todo_cli/reports.py
todo_cli/subtasks.py
agile_todo_cli-1.2.0.dist-info/METADATA
agile_todo_cli-1.2.0.dist-info/WHEEL
agile_todo_cli-1.2.0.dist-info/entry_points.txt
agile_todo_cli-1.2.0.dist-info/RECORD
