Metadata-Version: 2.4
Name: agile-todo-cli
Version: 1.2.0
Summary: CLI tool for managing daily todos with time tracking
Requires-Python: >=3.10
Requires-Dist: pyyaml>=6.0
Requires-Dist: rich>=13.0.0
Requires-Dist: textual>=0.47.0
Requires-Dist: typer[all]>=0.9.0
Provides-Extra: dev
Requires-Dist: pytest-cov>=4.0.0; extra == 'dev'
Requires-Dist: pytest>=7.0.0; extra == 'dev'
